{
  "version": "7",
  "dialect": "sqlite",
  "entries": [
    {
      "idx": 0,
      "version": "6",
      "when": 1776238251274,
      "tag": "0000_lumpy_bloodstorm",
      "breakpoints": true
    },
    {
      "idx": 1,
      "version": "6",
      "when": 1776243750097,
      "tag": "0001_flashy_blackheart",
      "breakpoints": true
    },
    {
      "idx": 2,
      "version": "6",
      "when": 1776266462800,
      "tag": "0002_dizzy_korvac",
      "breakpoints": true
    },
    {
      "idx": 3,
      "version": "6",
      "when": 1776310217495,
      "tag": "0003_demonic_skin",
      "breakpoints": true
    },
    {
      "idx": 4,
      "version": "6",
      "when": 1776313945281,
      "tag": "0004_mushy_betty_ross",
      "breakpoints": true
    },
    {
      "idx": 5,
      "version": "6",
      "when": 1776315762938,
      "tag": "0005_early_the_professor",
      "breakpoints": true
    },
    {
      "idx": 6,
      "version": "6",
      "when": 1776393536570,
      "tag": "0006_natural_rhodey",
      "breakpoints": true
    },
    {
      "idx": 7,
      "version": "6",
      "when": 1776396635155,
      "tag": "0007_true_exodus",
      "breakpoints": true
    },
    {
      "idx": 8,
      "version": "6",
      "when": 1776671140717,
      "tag": "0008_cuddly_molly_hayes",
      "breakpoints": true
    },
    {
      "idx": 9,
      "version": "6",
      "when": 1776674485076,
      "tag": "0009_fearless_whizzer",
      "breakpoints": true
    },
    {
      "idx": 10,
      "version": "6",
      "when": 1776730235092,
      "tag": "0010_misty_cobalt_man",
      "breakpoints": true
    },
    {
      "idx": 11,
      "version": "6",
      "when": 1776731422420,
      "tag": "0011_silent_vanisher",
      "breakpoints": true
    },
    {
      "idx": 12,
      "version": "6",
      "when": 1777435790459,
      "tag": "0012_dusty_excalibur",
      "breakpoints": true
    },
    {
      "idx": 13,
      "version": "6",
      "when": 1777443000944,
      "tag": "0013_fantastic_catseye",
      "breakpoints": true
    },
    {
      "idx": 14,
      "version": "6",
      "when": 1778128999552,
      "tag": "0014_skinny_scarlet_witch",
      "breakpoints": true
    },
    {
      "idx": 15,
      "version": "6",
      "when": 1778560622257,
      "tag": "0015_lyrical_speedball",
      "breakpoints": true
    },
    {
      "idx": 16,
      "version": "6",
      "when": 1778568485796,
      "tag": "0016_wet_rick_jones",
      "breakpoints": true
    },
    {
      "idx": 17,
      "version": "6",
      "when": 1778571707333,
      "tag": "0017_blushing_bruce_banner",
      "breakpoints": true
    },
    {
      "idx": 18,
      "version": "6",
      "when": 1783130522671,
      "tag": "0018_fancy_master_chief",
      "breakpoints": true
    },
    {
      "idx": 19,
      "version": "6",
      "when": 1783222881745,
      "tag": "0019_regular_screwball",
      "breakpoints": true
    },
    {
      "idx": 20,
      "version": "6",
      "when": 1783246066470,
      "tag": "0020_cool_firebrand",
      "breakpoints": true
    },
    {
      "idx": 21,
      "version": "6",
      "when": 1783297607757,
      "tag": "0021_new_darkhawk",
      "breakpoints": true
    },
    {
      "idx": 22,
      "version": "6",
      "when": 1783299187869,
      "tag": "0022_chemical_thena",
      "breakpoints": true
    },
    {
      "idx": 23,
      "version": "6",
      "when": 1783309240321,
      "tag": "0023_high_goblin_queen",
      "breakpoints": true
    },
    {
      "idx": 24,
      "version": "6",
      "when": 1783310296391,
      "tag": "0024_robust_arclight",
      "breakpoints": true
    }
  ]
}